{
  "_class": "artboard",
  "backgroundColor": {
    "_class": "color",
    "alpha": 1,
    "blue": 1,
    "green": 1,
    "red": 1
  },
  "booleanOperation": -1,
  "clippingMaskMode": 0,
  "do_objectID": "96BBCA25-6CB0-4E0C-8AF0-AB249156C49A",
  "exportOptions": {
    "_class": "exportOptions",
    "exportFormats": [
      {
        "_class": "exportFormat",
        "absoluteSize": 0,
        "fileFormat": "jpg",
        "name": "svg",
        "namingScheme": 0,
        "scale": 1,
        "visibleScaleType": 0
      }
    ],
    "includedLayerIds": [
    ],
    "layerOptions": 0,
    "shouldTrim": false
  },
  "frame": {
    "_class": "rect",
    "constrainProportions": false,
    "height": 768,
    "width": 1024,
    "x": 8299,
    "y": 4627
  },
  "groupLayout": {
    "_class": "MSImmutableFreeformGroupLayout"
  },
  "hasBackgroundColor": false,
  "hasClickThrough": false,
  "hasClippingMask": false,
  "horizontalRulerData": {
    "_class": "rulerData",
    "base": 0,
    "guides": [
    ]
  },
  "includeBackgroundColorInExport": true,
  "includeInCloudUpload": true,
  "isFixedToViewport": false,
  "isFlippedHorizontal": false,
  "isFlippedVertical": false,
  "isFlowHome": false,
  "isLocked": false,
  "isVisible": true,
  "layerListExpandedType": 2,
  "layers": [
    {
      "class": "symbolInstance",
      "id": "9ABC482C-870F-47D8-B155-5D1B7CA31166"
    },
    {
      "class": "symbolInstance",
      "id": "E9EB2F3F-01DB-4CDA-A056-4CD853A40261"
    },
    {
      "class": "symbolInstance",
      "id": "DF8D4A7B-F0C4-442A-ADA7-84A9B5E58ED6"
    },
    {
      "class": "symbolInstance",
      "id": "05229DF4-A451-4367-B480-FD6CFA489CE9"
    },
    {
      "class": "symbolInstance",
      "id": "9A6BA5C5-2382-4665-9B55-05B0A0DB4B28"
    },
    {
      "class": "symbolInstance",
      "id": "D7BE5294-56A4-4CC6-B96F-7C7806FE0247"
    },
    {
      "class": "symbolInstance",
      "id": "13396A1A-343A-4191-8B1A-033B11357949"
    },
    {
      "class": "symbolInstance",
      "id": "39953A3B-1EB5-4A09-8FC7-0631B78A51B2"
    },
    {
      "class": "symbolInstance",
      "id": "092FEE24-129C-41AD-802B-029EF2306EC0"
    },
    {
      "class": "symbolInstance",
      "id": "EE89830B-DE34-47DB-9603-6CA05B969E96"
    },
    {
      "class": "symbolInstance",
      "id": "09746271-A1D1-47F1-B624-A43BD7F92930"
    }
  ],
  "maintainScrollPosition": false,
  "name": "Survey Copy",
  "nameIsFixed": true,
  "presetDictionary": {
    "allowResizedMatching": 0,
    "height": 768,
    "name": "7.9” iPad mini",
    "offersLandscapeVariant": 1,
    "width": 1024
  },
  "resizesContent": false,
  "resizingConstraint": 63,
  "resizingType": 0,
  "rotation": 0,
  "shouldBreakMaskChain": true,
  "style": {
    "_class": "style",
    "blur": {
      "_class": "blur",
      "center": "{0.5, 0.5}",
      "isEnabled": false,
      "motionAngle": 0,
      "radius": 10,
      "saturation": 1,
      "type": 0
    },
    "borderOptions": {
      "_class": "borderOptions",
      "dashPattern": [
      ],
      "isEnabled": true,
      "lineCapStyle": 0,
      "lineJoinStyle": 0
    },
    "borders": [
    ],
    "colorControls": {
      "_class": "colorControls",
      "brightness": 0,
      "contrast": 1,
      "hue": 0,
      "isEnabled": false,
      "saturation": 1
    },
    "contextSettings": {
      "_class": "graphicsContextSettings",
      "blendMode": 0,
      "opacity": 1
    },
    "do_objectID": "A3D3CF09-0950-4E51-B05C-7633E728AEA5",
    "endMarkerType": 0,
    "fills": [
    ],
    "innerShadows": [
    ],
    "miterLimit": 10,
    "shadows": [
    ],
    "startMarkerType": 0,
    "windingRule": 1
  },
  "verticalRulerData": {
    "_class": "rulerData",
    "base": 0,
    "guides": [
    ]
  }
}